DonutLLMCore.py
DonutLLMCore-1.0.0.dist-info/LICENSE
DonutLLMCore-1.0.0.dist-info/METADATA
DonutLLMCore-1.0.0.dist-info/WHEEL
DonutLLMCore-1.0.0.dist-info/top_level.txt
DonutLLMCore-1.0.0.dist-info/RECORD
