Metadata-Version: 2.1
Name: DonutLLMCore
Version: 1.0.0
Summary: Core library for training PyTorch model in Donut-LLM-Tools
Home-page: https://github.com/gauthamnair2005/donutllmcore
Author: Gautham Nair
Author-email: gautham.nair.2005@gmail.com
License: MIT License
Keywords: AI,ML,Train,Model,Dataset
Classifier: License :: OSI Approved :: MIT License
Classifier: Programming Language :: Python :: 3
Requires-Python: <3.12,>=3.9
License-File: LICENSE
Requires-Dist: torch
Requires-Dist: torchvision
Requires-Dist: torchaudio
Requires-Dist: dill
Provides-Extra: dev
Requires-Dist: black ; extra == 'dev'
Requires-Dist: bumpver ; extra == 'dev'
Requires-Dist: isort ; extra == 'dev'
Requires-Dist: pip-tools ; extra == 'dev'
Requires-Dist: pytest ; extra == 'dev'
